{
	"Adorf": {
		"regex": "^A-.*",
		"filename": "adorf.json",
		"domain_code": "ffv_a",
		"tags": [
			"place",
			"municipality"
		]
	},
	"Auerbach": {
		"regex": "^AE-.*",
		"filename": "auerbach.json",
		"domain_code": "ffv_ae",
		"tags": [
			"place",
			"municipality"
		]
	},
	"Bad Brambach": {
		"regex": "^BB-.*",
		"filename": "bad-brambach.json",
		"domain_code": "ffv_bb",
		"tags": [
			"place",
			"municipality"
		]
	},
	"Bad Elster": {
		"regex": "^BE-.*",
		"filename": "bad-elster.json",
		"domain_code": "ffv_be",
		"tags": [
			"place",
			"municipality"
		]
	},
	"Bergen": {
		"regex": "^B-.*",
		"filename": "bergen.json",
		"domain_code": "ffv_b",
		"tags": [
			"place",
			"municipality"
		]
	},
	"Bösenbrunn": {
		"regex": "^BOE-.*",
		"filename": "bösenbrunn.json",
		"domain_code": "ffv_boe",
		"tags": [
			"place",
			"municipality"
		]
	},
	"Eichigt": {
		"regex": "^EIC-.*",
		"filename": "eichigt.json",
		"domain_code": "ffv_eic",
		"tags": [
			"place",
			"municipality"
		]
	},
	"Ellefeld": {
		"regex": "^ELL-.*",
		"filename": "ellefeld.json",
		"domain_code": "ffv_ell",
		"tags": [
			"place",
			"municipality"
		]
	},
	"Elsterberg": {
		"regex": "^ELS-.*",
		"filename": "elsterberg.json",
		"domain_code": "ffv_els",
		"tags": [
			"place",
			"municipality"
		]
	},
	"Falkenstein": {
		"regex": "^FST-.*",
		"filename": "falkenstein.json",
		"domain_code": "ffv_fst",
		"tags": [
			"place",
			"municipality"
		]
	},
	"Grünbach": {
		"regex": "^GB-.*",
		"filename": "gruenbach.json",
		"domain_code": "ffv_gb",
		"tags": [
			"place",
			"municipality"
		]
	},
	"Heinsdorfergrund": {
		"regex": "^HDG-.*",
		"filename": "heinsdorfergrund.json",
		"domain_code": "ffv_hdg",
		"tags": [
			"place",
			"municipality"
		]
	},
	"Klingenthal": {
		"regex": "^K-.*",
		"filename": "klingenthal.json",
		"domain_code": "ffv_k",
		"tags": [
			"place",
			"municipality"
		]
	},
	"Lengenfeld": {
		"regex": "^LE-.*",
		"filename": "lengenfeld.json",
		"domain_code": "ffv_le",
		"tags": [
			"place",
			"municipality"
		]
	},
	"Limbach": {
		"regex": "^L-.*",
		"filename": "limbach.json",
		"domain_code": "ffv_l",
		"tags": [
			"place",
			"municipality"
		]
	},
	"Markneukirchen": {
		"regex": "^MKN-.*",
		"filename": "markneukirchen.json",
		"domain_code": "ffv_mkn",
		"tags": [
			"place",
			"municipality"
		]
	},
	"Mühlental": {
		"regex": "^MTL-.*",
		"filename": "muehlental.json",
		"domain_code": "ffv_mtl",
		"tags": [
			"place",
			"municipality"
		]
	},
	"Muldenhammer": {
		"regex": "^MH-.*",
		"filename": "muldenhammer.json",
		"domain_code": "ffv_mh",
		"tags": [
			"place",
			"municipality"
		]
	},
	"Netzschkau": {
		"regex": "^N-.*",
		"filename": "netzschkau.json",
		"domain_code": "ffv_n",
		"tags": [
			"place",
			"municipality"
		]
	},
	"Neuensalz": {
		"regex": "^NSZ-.*",
		"filename": "neuensalz.json",
		"domain_code": "ffv_nsz",
		"tags": [
			"place",
			"municipality"
		]
	},
	"Neumark": {
		"regex": "^NMK-.*",
		"filename": "neumark.json",
		"domain_code": "ffv_nmk",
		"tags": [
			"place",
			"municipality"
		]
	},
	"Neustadt": {
		"regex": "^NST-.*",
		"filename": "neustadt.json",
		"domain_code": "ffv_nst",
		"tags": [
			"place",
			"municipality"
		]
	},
	"Oelsnitz": {
		"regex": "^OEL-.*",
		"filename": "oelsnitz.json",
		"domain_code": "ffv_oel",
		"tags": [
			"place",
			"municipality"
		]
	},
	"Pausa-Mühltroff": {
		"regex": "^PMF-.*",
		"filename": "pausa-muehltroff.json",
		"domain_code": "ffv_pmf",
		"tags": [
			"place",
			"municipality"
		]
	},
	"Plauen": {
		"regex": "^PL-.*",
		"filename": "plauen.json",
		"domain_code": "ffv_pl",
		"tags": [
			"place",
			"municipality"
		]
	},
	"Pöhl": {
		"regex": "^POE-.*",
		"filename": "poehl.json",
		"domain_code": "ffv_poe",
		"tags": [
			"place",
			"municipality"
		]
	},
	"Reichenbach": {
		"regex": "^RC-.*",
		"filename": "reichenbach.json",
		"domain_code": "ffv_rc",
		"tags": [
			"place",
			"municipality"
		]
	},
	"Rodewisch": {
		"regex": "^RDW-.*",
		"filename": "rodewisch.json",
		"domain_code": "ffv_rdw",
		"tags": [
			"place",
			"municipality"
		]
	},
	"Rosenbach": {
		"regex": "^RBH-.*",
		"filename": "rosenbach.json",
		"tags": [
			"place",
			"municipality"
		]
	},
	"Schöneck": {
		"regex": "^S-.*",
		"filename": "schoeneck.json",
		"domain_code": "ffv_s",
		"tags": [
			"place",
			"municipality"
		]
	},
	"Steinberg": {
		"regex": "^SBG-.*",
		"filename": "steinberg.json",
		"domain_code": "ffv_sbg",
		"tags": [
			"place",
			"municipality"
		]
	},
	"Theuma": {
		"regex": "^T-.*",
		"filename": "theuma.json",
		"domain_code": "ffv_t",
		"tags": [
			"place",
			"municipality"
		]
	},
	"Tirpersdorf": {
		"regex": "^TDF-.*",
		"filename": "tirpersdorf.json",
		"domain_code": "ffv_tdf",
		"tags": [
			"place",
			"municipality"
		]
	},
	"Treuen": {
		"regex": "^TR-.*",
		"filename": "treuen.json",
		"domain_code": "ffv_tr",
		"tags": [
			"place",
			"municipality"
		]
	},
	"Triebel": {
		"regex": "^TRI-.*",
		"filename": "triebel.json",
		"domain_code": "ffv_tri",
		"tags": [
			"place",
			"municipality"
		]
	},
	"Weischlitz": {
		"regex": "^WEI-.*",
		"filename": "weischlitz.json",
		"domain_code": "ffv_wei",
		"tags": [
			"place",
			"municipality"
		]
	},
	"Werda": {
		"regex": "^WER-.*",
		"filename": "werda.json",
		"domain_code": "ffv_wer",
		"tags": [
			"place",
			"municipality"
		]
	},
	"City-Hotel": {
		"regex": "^PL-Neundorfer23-City-Hotel.*",
		"filename": "city-hotel.json",
		"tags": [
			"place",
			"venue"
		]
	},
	"Hotel Alexandra": {
		"regex": "^PL-Bahnhof17-HotelAlexandra.*",
		"filename": "hotel-alexandra.json",
		"tags": [
			"place",
			"venue"
		]
	},
	"Zum Kerkermeister - Auerbach": {
		"regex": "^AE-Kirchpl1-Kerkermeister*",
		"filename": "zum-kerkermeister.json",
		"tags": [
			"place",
			"venue"
		]
	},
	"Parkhotel": {
		"regex": "^PL-Raedel18-(Parkhotel-.*|FriesischeBotschaft)",
		"filename": "parkhotel.json",
		"tags": [
			"place",
			"venue"
		]
	},
	"PL-Johanniskirche": {
		"regex": "^PL-Johanniskirche-.*",
		"filename": "pl_johanniskirche.json",
		"tags": [
			"place",
			"venue"
		]
	},
	"KlangGarten - Kurzfilm- & Musikfestival": {
		"regex": "^PL-(Walkgasse7-ViVo|Bleich3-WeisbachschesHaus-\\d|FFV-Klanggarten\\d)",
		"filename": "klanggarten.json",
		"tags": [
			"place",
			"event"
		]
	}
}
